puhuo_mcp_server/__init__.py
puhuo_mcp_server/server.py
puhuo_mcp_server-0.1.5.dist-info/METADATA
puhuo_mcp_server-0.1.5.dist-info/WHEEL
puhuo_mcp_server-0.1.5.dist-info/entry_points.txt
puhuo_mcp_server-0.1.5.dist-info/RECORD
