Metadata-Version: 2.4
Name: puhuo-mcp-server
Version: 0.1.5
Summary: 普货 MCP 服务器，提供运单号拦截和快递公司编码查询功能
Author-email: "wuzhang.wz" <wuzhang.wz@alibaba-inc.com>
Requires-Python: >=3.10
Requires-Dist: fastmcp>=2.10.5
Requires-Dist: mcp[cli]>=1.10.1
Requires-Dist: requests>=2.31.0
